nonebot_plugin_game_tools/__init__.py
nonebot_plugin_game_tools/__version__.py
nonebot_plugin_game_tools/config.py
nonebot_plugin_game_tools-1.0.6.dist-info/licenses/LICENSE
nonebot_plugin_game_tools-1.0.6.dist-info/METADATA
nonebot_plugin_game_tools-1.0.6.dist-info/WHEEL
nonebot_plugin_game_tools-1.0.6.dist-info/top_level.txt
nonebot_plugin_game_tools-1.0.6.dist-info/RECORD
