Metadata-Version: 2.4
Name: nonebot_plugin_game_tools
Version: 1.0.6
Summary: 游戏工具插件.
Home-page: https://github.com/snowrabbit-top/nonebot_plugin_game_tools
Author: SnowRabbit
Author-email: snowrabbit@snowrabbit.top
License: MIT
Classifier: License :: OSI Approved :: MIT License
Classifier: Programming Language :: Python
Classifier: Programming Language :: Python :: 3
Classifier: Programming Language :: Python :: 3.9
Classifier: Programming Language :: Python :: Implementation :: CPython
Classifier: Programming Language :: Python :: Implementation :: PyPy
Requires-Python: >=3.9.0
License-File: LICENSE
Requires-Dist: nonebot2
Dynamic: author
Dynamic: author-email
Dynamic: classifier
Dynamic: description
Dynamic: description-content-type
Dynamic: home-page
Dynamic: license
Dynamic: license-file
Dynamic: requires-dist
Dynamic: requires-python
Dynamic: summary
